pymegle/__init__.py
pymegle/chat.py
pymegle/core.py
pymegle/exceptions.py
pymegle/log.py
pymegle/userclient.py
pymegle-0.0.2.dist-info/LICENSE
pymegle-0.0.2.dist-info/METADATA
pymegle-0.0.2.dist-info/WHEEL
pymegle-0.0.2.dist-info/top_level.txt
pymegle-0.0.2.dist-info/RECORD
