Metadata-Version: 2.1
Name: pymegle
Version: 0.0.2
Summary: Unofficial Omegle API with built in user client
Home-page: https://github.com/jennissenevan/pymegle
Author: Evan Jennissen
Author-email: jennissenevan@gmail.com
License: UNKNOWN
Platform: UNKNOWN
Classifier: Programming Language :: Python :: 3
Classifier: License :: OSI Approved :: MIT License
Classifier: Operating System :: OS Independent
Requires-Python: >=3.9
License-File: LICENSE
Requires-Dist: aiohttp
Requires-Dist: aioconsole
Requires-Dist: pynput
